libspg/__init__.py
libspg/bdo.py
libspg-0.2.dist-info/DESCRIPTION.rst
libspg-0.2.dist-info/METADATA
libspg-0.2.dist-info/metadata.json
libspg-0.2.dist-info/pbr.json
libspg-0.2.dist-info/RECORD
libspg-0.2.dist-info/top_level.txt
libspg-0.2.dist-info/WHEEL
