Metadata-Version: 2.0
Name: libspg
Version: 0.2
Summary: Python library for interacting with Brazil NPAC SPG
Home-page: http://bitbucket.org/asenci/libspg
Author: Andre Sencioles Vitorio Oliveira
Author-email: andre@bcp.net.br
License: ISC License
Keywords: BDO,LNP,NPAC,SOA,SPG
Platform: any
Classifier: Natural Language :: English
Classifier: Operating System :: MacOS :: MacOS X
Classifier: Operating System :: POSIX
Classifier: Operating System :: POSIX :: BSD
Classifier: Operating System :: POSIX :: Linux
Classifier: Operating System :: Microsoft :: Windows
Classifier: Programming Language :: Python
Classifier: Programming Language :: Python :: 2
Classifier: Programming Language :: Python :: 2.6
Classifier: Programming Language :: Python :: 2.7
Classifier: Programming Language :: Python :: Implementation :: CPython
Requires-Dist: lxml
